peakrdl_sv/__init__.py
peakrdl_sv/__peakrdl__.py
peakrdl_sv/exporter.py
peakrdl_sv/main.py
peakrdl_sv/reg_pkg.sv.tpl
peakrdl_sv/reg_top.sv.tpl
peakrdl_sv/data/rdl_subreg.sv
peakrdl_sv/data/rdl_subreg_arb.sv
peakrdl_sv/data/rdl_subreg_flop.sv
peakrdl_sv/data/rdl_subreg_pkg.sv
peakrdl_sv-0.0.1.dist-info/METADATA
peakrdl_sv-0.0.1.dist-info/WHEEL
peakrdl_sv-0.0.1.dist-info/entry_points.txt
peakrdl_sv-0.0.1.dist-info/top_level.txt
peakrdl_sv-0.0.1.dist-info/RECORD
