Metadata-Version: 2.1
Name: peakrdl-sv
Version: 0.0.1
Summary: A SystemRDL exporter for SystemVerilog 
Author-email: Shareef Jalloq <shareef@nu-quantum.com>
Keywords: SystemRDL,exporter,SystemVerilog,Verilog,Register File,Register,CSR
Classifier: License :: OSI Approved :: MIT License
Classifier: Programming Language :: Python :: 3.9
Classifier: Programming Language :: Python :: 3.10
Requires-Python: >=3.9
Requires-Dist: systemrdl-compiler
Requires-Dist: peakrdl
Requires-Dist: mako
